<?xml version="1.0" encoding="UTF-8"?>
<!DOCTYPE mapper PUBLIC "-//mybatis.org//DTD Mapper 3.0//EN" "http://mybatis.org/dtd/mybatis-3-mapper.dtd">
<mapper namespace="liu.mapper.PatientMapper">
  <resultMap id="BaseResultMap" type="liu.bean.Patient">
    <!--
      WARNING - @mbggenerated
      This element is automatically generated by MyBatis Generator, do not modify.
      This element was generated on Thu Dec 29 21:08:19 CST 2022.
    -->
    <id column="PATIENT_NO" jdbcType="INTEGER" property="patientNo" />
    <result column="PATIENT_NAME" jdbcType="VARCHAR" property="patientName" />
    <result column="PATIENT_GENDER" jdbcType="CHAR" property="patientGender" />
    <result column="PATIENT_DATE_START" jdbcType="VARCHAR" property="patientDateStart" />
    <result column="PATIENT_DEPT" jdbcType="INTEGER" property="patientDept" />
    <result column="PATIENT_STATE" jdbcType="VARCHAR" property="patientState" />
    <result column="PATIENT_DOC" jdbcType="INTEGER" property="patientDoc" />
    <result column="PATIENT_ROOM" jdbcType="INTEGER" property="patientRoom" />
    <result column="PATIENT_BE" jdbcType="INTEGER" property="patientBe" />
  </resultMap>
  <sql id="Example_Where_Clause">
    <!--
      WARNING - @mbggenerated
      This element is automatically generated by MyBatis Generator, do not modify.
      This element was generated on Thu Dec 29 21:08:19 CST 2022.
    -->
    <where>
      <foreach collection="oredCriteria" item="criteria" separator="or">
        <if test="criteria.valid">
          <trim prefix="(" prefixOverrides="and" suffix=")">
            <foreach collection="criteria.criteria" item="criterion">
              <choose>
                <when test="criterion.noValue">
                  and ${criterion.condition}
                </when>
                <when test="criterion.singleValue">
                  and ${criterion.condition} #{criterion.value}
                </when>
                <when test="criterion.betweenValue">
                  and ${criterion.condition} #{criterion.value} and #{criterion.secondValue}
                </when>
                <when test="criterion.listValue">
                  and ${criterion.condition}
                  <foreach close=")" collection="criterion.value" item="listItem" open="(" separator=",">
                    #{listItem}
                  </foreach>
                </when>
              </choose>
            </foreach>
          </trim>
        </if>
      </foreach>
    </where>
  </sql>
  <sql id="Update_By_Example_Where_Clause">
    <!--
      WARNING - @mbggenerated
      This element is automatically generated by MyBatis Generator, do not modify.
      This element was generated on Thu Dec 29 21:08:19 CST 2022.
    -->
    <where>
      <foreach collection="example.oredCriteria" item="criteria" separator="or">
        <if test="criteria.valid">
          <trim prefix="(" prefixOverrides="and" suffix=")">
            <foreach collection="criteria.criteria" item="criterion">
              <choose>
                <when test="criterion.noValue">
                  and ${criterion.condition}
                </when>
                <when test="criterion.singleValue">
                  and ${criterion.condition} #{criterion.value}
                </when>
                <when test="criterion.betweenValue">
                  and ${criterion.condition} #{criterion.value} and #{criterion.secondValue}
                </when>
                <when test="criterion.listValue">
                  and ${criterion.condition}
                  <foreach close=")" collection="criterion.value" item="listItem" open="(" separator=",">
                    #{listItem}
                  </foreach>
                </when>
              </choose>
            </foreach>
          </trim>
        </if>
      </foreach>
    </where>
  </sql>
  <sql id="Base_Column_List">
    <!--
      WARNING - @mbggenerated
      This element is automatically generated by MyBatis Generator, do not modify.
      This element was generated on Thu Dec 29 21:08:19 CST 2022.
    -->
    PATIENT_NO, PATIENT_NAME, PATIENT_GENDER, PATIENT_DATE_START, PATIENT_DEPT, PATIENT_STATE, 
    PATIENT_DOC, PATIENT_ROOM, PATIENT_BE
  </sql>
  <select id="selectByExample" parameterType="liu.bean.PatientExample" resultMap="BaseResultMap">
    <!--
      WARNING - @mbggenerated
      This element is automatically generated by MyBatis Generator, do not modify.
      This element was generated on Thu Dec 29 21:08:19 CST 2022.
    -->
    select
    <if test="distinct">
      distinct
    </if>
    <include refid="Base_Column_List" />
    from patient
    <if test="_parameter != null">
      <include refid="Example_Where_Clause" />
    </if>
    <if test="orderByClause != null">
      order by ${orderByClause}
    </if>
  </select>
  <select id="selectByPrimaryKey" parameterType="java.lang.Integer" resultMap="BaseResultMap">
    <!--
      WARNING - @mbggenerated
      This element is automatically generated by MyBatis Generator, do not modify.
      This element was generated on Thu Dec 29 21:08:19 CST 2022.
    -->
    select 
    <include refid="Base_Column_List" />
    from patient
    where PATIENT_NO = #{patientNo,jdbcType=INTEGER}
  </select>
  <delete id="deleteByPrimaryKey" parameterType="java.lang.Integer">
    <!--
      WARNING - @mbggenerated
      This element is automatically generated by MyBatis Generator, do not modify.
      This element was generated on Thu Dec 29 21:08:19 CST 2022.
    -->
    delete from patient
    where PATIENT_NO = #{patientNo,jdbcType=INTEGER}
  </delete>
  <delete id="deleteByExample" parameterType="liu.bean.PatientExample">
    <!--
      WARNING - @mbggenerated
      This element is automatically generated by MyBatis Generator, do not modify.
      This element was generated on Thu Dec 29 21:08:19 CST 2022.
    -->
    delete from patient
    <if test="_parameter != null">
      <include refid="Example_Where_Clause" />
    </if>
  </delete>
  <insert id="insert" parameterType="liu.bean.Patient">
    <!--
      WARNING - @mbggenerated
      This element is automatically generated by MyBatis Generator, do not modify.
      This element was generated on Thu Dec 29 21:08:19 CST 2022.
    -->
    insert into patient (PATIENT_NO, PATIENT_NAME, PATIENT_GENDER, 
      PATIENT_DATE_START, PATIENT_DEPT, PATIENT_STATE, 
      PATIENT_DOC, PATIENT_ROOM, PATIENT_BE
      )
    values (#{patientNo,jdbcType=INTEGER}, #{patientName,jdbcType=VARCHAR}, #{patientGender,jdbcType=CHAR}, 
      #{patientDateStart,jdbcType=VARCHAR}, #{patientDept,jdbcType=INTEGER}, #{patientState,jdbcType=VARCHAR}, 
      #{patientDoc,jdbcType=INTEGER}, #{patientRoom,jdbcType=INTEGER}, #{patientBe,jdbcType=INTEGER}
      )
  </insert>
  <insert id="insertSelective" parameterType="liu.bean.Patient">
    <!--
      WARNING - @mbggenerated
      This element is automatically generated by MyBatis Generator, do not modify.
      This element was generated on Thu Dec 29 21:08:19 CST 2022.
    -->
    insert into patient
    <trim prefix="(" suffix=")" suffixOverrides=",">
      <if test="patientNo != null">
        PATIENT_NO,
      </if>
      <if test="patientName != null">
        PATIENT_NAME,
      </if>
      <if test="patientGender != null">
        PATIENT_GENDER,
      </if>
      <if test="patientDateStart != null">
        PATIENT_DATE_START,
      </if>
      <if test="patientDept != null">
        PATIENT_DEPT,
      </if>
      <if test="patientState != null">
        PATIENT_STATE,
      </if>
      <if test="patientDoc != null">
        PATIENT_DOC,
      </if>
      <if test="patientRoom != null">
        PATIENT_ROOM,
      </if>
      <if test="patientBe != null">
        PATIENT_BE,
      </if>
    </trim>
    <trim prefix="values (" suffix=")" suffixOverrides=",">
      <if test="patientNo != null">
        #{patientNo,jdbcType=INTEGER},
      </if>
      <if test="patientName != null">
        #{patientName,jdbcType=VARCHAR},
      </if>
      <if test="patientGender != null">
        #{patientGender,jdbcType=CHAR},
      </if>
      <if test="patientDateStart != null">
        #{patientDateStart,jdbcType=VARCHAR},
      </if>
      <if test="patientDept != null">
        #{patientDept,jdbcType=INTEGER},
      </if>
      <if test="patientState != null">
        #{patientState,jdbcType=VARCHAR},
      </if>
      <if test="patientDoc != null">
        #{patientDoc,jdbcType=INTEGER},
      </if>
      <if test="patientRoom != null">
        #{patientRoom,jdbcType=INTEGER},
      </if>
      <if test="patientBe != null">
        #{patientBe,jdbcType=INTEGER},
      </if>
    </trim>
  </insert>
  <select id="countByExample" parameterType="liu.bean.PatientExample" resultType="java.lang.Integer">
    <!--
      WARNING - @mbggenerated
      This element is automatically generated by MyBatis Generator, do not modify.
      This element was generated on Thu Dec 29 21:08:19 CST 2022.
    -->
    select count(*) from patient
    <if test="_parameter != null">
      <include refid="Example_Where_Clause" />
    </if>
  </select>
  <update id="updateByExampleSelective" parameterType="map">
    <!--
      WARNING - @mbggenerated
      This element is automatically generated by MyBatis Generator, do not modify.
      This element was generated on Thu Dec 29 21:08:19 CST 2022.
    -->
    update patient
    <set>
      <if test="record.patientNo != null">
        PATIENT_NO = #{record.patientNo,jdbcType=INTEGER},
      </if>
      <if test="record.patientName != null">
        PATIENT_NAME = #{record.patientName,jdbcType=VARCHAR},
      </if>
      <if test="record.patientGender != null">
        PATIENT_GENDER = #{record.patientGender,jdbcType=CHAR},
      </if>
      <if test="record.patientDateStart != null">
        PATIENT_DATE_START = #{record.patientDateStart,jdbcType=VARCHAR},
      </if>
      <if test="record.patientDept != null">
        PATIENT_DEPT = #{record.patientDept,jdbcType=INTEGER},
      </if>
      <if test="record.patientState != null">
        PATIENT_STATE = #{record.patientState,jdbcType=VARCHAR},
      </if>
      <if test="record.patientDoc != null">
        PATIENT_DOC = #{record.patientDoc,jdbcType=INTEGER},
      </if>
      <if test="record.patientRoom != null">
        PATIENT_ROOM = #{record.patientRoom,jdbcType=INTEGER},
      </if>
      <if test="record.patientBe != null">
        PATIENT_BE = #{record.patientBe,jdbcType=INTEGER},
      </if>
    </set>
    <if test="_parameter != null">
      <include refid="Update_By_Example_Where_Clause" />
    </if>
  </update>
  <update id="updateByExample" parameterType="map">
    <!--
      WARNING - @mbggenerated
      This element is automatically generated by MyBatis Generator, do not modify.
      This element was generated on Thu Dec 29 21:08:19 CST 2022.
    -->
    update patient
    set PATIENT_NO = #{record.patientNo,jdbcType=INTEGER},
      PATIENT_NAME = #{record.patientName,jdbcType=VARCHAR},
      PATIENT_GENDER = #{record.patientGender,jdbcType=CHAR},
      PATIENT_DATE_START = #{record.patientDateStart,jdbcType=VARCHAR},
      PATIENT_DEPT = #{record.patientDept,jdbcType=INTEGER},
      PATIENT_STATE = #{record.patientState,jdbcType=VARCHAR},
      PATIENT_DOC = #{record.patientDoc,jdbcType=INTEGER},
      PATIENT_ROOM = #{record.patientRoom,jdbcType=INTEGER},
      PATIENT_BE = #{record.patientBe,jdbcType=INTEGER}
    <if test="_parameter != null">
      <include refid="Update_By_Example_Where_Clause" />
    </if>
  </update>
  <update id="updateByPrimaryKeySelective" parameterType="liu.bean.Patient">
    <!--
      WARNING - @mbggenerated
      This element is automatically generated by MyBatis Generator, do not modify.
      This element was generated on Thu Dec 29 21:08:19 CST 2022.
    -->
    update patient
    <set>
      <if test="patientName != null">
        PATIENT_NAME = #{patientName,jdbcType=VARCHAR},
      </if>
      <if test="patientGender != null">
        PATIENT_GENDER = #{patientGender,jdbcType=CHAR},
      </if>
      <if test="patientDateStart != null">
        PATIENT_DATE_START = #{patientDateStart,jdbcType=VARCHAR},
      </if>
      <if test="patientDept != null">
        PATIENT_DEPT = #{patientDept,jdbcType=INTEGER},
      </if>
      <if test="patientState != null">
        PATIENT_STATE = #{patientState,jdbcType=VARCHAR},
      </if>
      <if test="patientDoc != null">
        PATIENT_DOC = #{patientDoc,jdbcType=INTEGER},
      </if>
      <if test="patientRoom != null">
        PATIENT_ROOM = #{patientRoom,jdbcType=INTEGER},
      </if>
      <if test="patientBe != null">
        PATIENT_BE = #{patientBe,jdbcType=INTEGER},
      </if>
    </set>
    where PATIENT_NO = #{patientNo,jdbcType=INTEGER}
  </update>
  <update id="updateByPrimaryKey" parameterType="liu.bean.Patient">
    <!--
      WARNING - @mbggenerated
      This element is automatically generated by MyBatis Generator, do not modify.
      This element was generated on Thu Dec 29 21:08:19 CST 2022.
    -->
    update patient
    set PATIENT_NAME = #{patientName,jdbcType=VARCHAR},
      PATIENT_GENDER = #{patientGender,jdbcType=CHAR},
      PATIENT_DATE_START = #{patientDateStart,jdbcType=VARCHAR},
      PATIENT_DEPT = #{patientDept,jdbcType=INTEGER},
      PATIENT_STATE = #{patientState,jdbcType=VARCHAR},
      PATIENT_DOC = #{patientDoc,jdbcType=INTEGER},
      PATIENT_ROOM = #{patientRoom,jdbcType=INTEGER},
      PATIENT_BE = #{patientBe,jdbcType=INTEGER}
    where PATIENT_NO = #{patientNo,jdbcType=INTEGER}
  </update>
</mapper>